[
  {
    "full_name": "withspectrum/spectrum",
    "stargazers_count": 9362,
    "open_issues_count": 312,
    "forks_count": 988
  },
  {
    "full_name": "mattermost/mattermost-server",
    "stargazers_count": 19355,
    "open_issues_count": 658,
    "forks_count": 4644
  },
  {
    "full_name": "microsoft/TypeScript",
    "stargazers_count": 65719,
    "open_issues_count": 4824,
    "forks_count": 8797
  },
  {
    "full_name": "nodejs/node",
    "stargazers_count": 74810,
    "open_issues_count": 1223,
    "forks_count": 18544
  },
  {
    "full_name": "excalidraw/excalidraw",
    "stargazers_count": 12719,
    "open_issues_count": 233,
    "forks_count": 871
  },
  {
    "full_name": "open-sauced/open-sauced",
    "stargazers_count": 306,
    "open_issues_count": 27,
    "forks_count": 86
  },
  {
    "full_name": "anuraghazra/github-readme-stats",
    "stargazers_count": 13762,
    "open_issues_count": 172,
    "forks_count": 2750
  }
]